gremlin_python/__init__.py
gremlin_python/__version__.py
gremlin_python/statics.py
gremlin_python/driver/__init__.py
gremlin_python/driver/client.py
gremlin_python/driver/connection.py
gremlin_python/driver/driver_remote_connection.py
gremlin_python/driver/protocol.py
gremlin_python/driver/remote_connection.py
gremlin_python/driver/request.py
gremlin_python/driver/resultset.py
gremlin_python/driver/serializer.py
gremlin_python/driver/transport.py
gremlin_python/driver/useragent.py
gremlin_python/driver/aiohttp/__init__.py
gremlin_python/driver/aiohttp/transport.py
gremlin_python/process/__init__.py
gremlin_python/process/anonymous_traversal.py
gremlin_python/process/graph_traversal.py
gremlin_python/process/strategies.py
gremlin_python/process/translator.py
gremlin_python/process/traversal.py
gremlin_python/structure/__init__.py
gremlin_python/structure/graph.py
gremlin_python/structure/io/__init__.py
gremlin_python/structure/io/graphbinaryV1.py
gremlin_python/structure/io/graphsonV2d0.py
gremlin_python/structure/io/graphsonV3d0.py
gremlin_python/structure/io/util.py
gremlinpython-3.7.5.dist-info/licenses/LICENSE
gremlinpython-3.7.5.dist-info/licenses/NOTICE
gremlinpython-3.7.5.dist-info/METADATA
gremlinpython-3.7.5.dist-info/WHEEL
gremlinpython-3.7.5.dist-info/top_level.txt
gremlinpython-3.7.5.dist-info/RECORD
