Metadata-Version: 2.4
Name: gremlinpython
Version: 3.7.5
Summary: Gremlin-Python for Apache TinkerPop
Maintainer-email: Apache TinkerPop <dev@tinkerpop.apache.org>
License: Apache 2
Project-URL: Homepage, https://tinkerpop.apache.org
Classifier: Intended Audience :: Developers
Classifier: License :: OSI Approved :: Apache Software License
Classifier: Natural Language :: English
Classifier: Programming Language :: Python :: 3
Requires-Python: >=3.9
License-File: LICENSE
License-File: NOTICE
Requires-Dist: nest_asyncio
Requires-Dist: aiohttp<4.0.0,>=3.8.0
Requires-Dist: aenum<4.0.0,>=1.4.5
Requires-Dist: isodate<1.0.0,>=0.6.0
Requires-Dist: async-timeout<5.0.0,>=4.0.3
Provides-Extra: kerberos
Requires-Dist: kerberos<2.0.0,>=1.3.0; extra == "kerberos"
Provides-Extra: ujson
Requires-Dist: ujson>=2.0.0; extra == "ujson"
Provides-Extra: test
Requires-Dist: pytest<7.2.0,>=4.6.4; extra == "test"
Requires-Dist: radish-bdd==0.18.2; extra == "test"
Requires-Dist: PyHamcrest<3.0.0,>=1.9.0; extra == "test"
Requires-Dist: PyYAML>=5.3; extra == "test"
Dynamic: license-file
